{"name": "Cours_d'eau_issu_des_Pyrénées", "id": 1034321, "predecessors": [{"name": "Cours_d'eau", "id": 87053}, {"name": "Europe", "id": 82819}], "successors": [{"name": "Cours_d'eau_en_Haute-Garonne", "id": 291736}, {"name": "Cours_d'eau_dans_l'Ariège", "id": 306197}, {"name": "Cours_d'eau_dans_l'Aude", "id": 362095}, {"name": "Cours_d'eau_dans_les_Pyrénées-Atlantiques", "id": 369418}, {"name": "Cours_d'eau_dans_les_Hautes-Pyrénées", "id": 739417}, {"name": "Cours_d'eau_dans_les_Pyrénées-Orientales", "id": 804963}, {"name": "Système_hydrologique_de_la_Garonne", "id": 3843851}]}