{"name": "Aude", "id": 120897, "predecessors": [{"name": "XVIIIe_siècle", "id": 1369784}, {"name": "Europe", "id": 82819}, {"name": "Administration_territoriale", "id": 434707}], "successors": [{"name": "Château_dans_l'Aude", "id": 945622}, {"name": "Monument_historique_dans_l'Aude", "id": 2832804}, {"name": "Naissance_dans_l'Aude", "id": 3102018}, {"name": "Décès_dans_l'Aude", "id": 6649150}, {"name": "Site_classé_ou_inscrit_dans_l'Aude", "id": 1144496}, {"name": "Élection_dans_l'Aude", "id": 14316651}, {"name": "Aire_d'attraction_de_Toulouse", "id": 15264482}, {"name": "Aire_d'attraction_de_Carcassonne", "id": 15288517}, {"name": "Aire_d'attraction_de_Limoux", "id": 15291291}, {"name": "Aire_d'attraction_de_Narbonne", "id": 15294636}]}