{"name": "Personnalité_liée_à_Angers", "id": 12102837, "predecessors": [{"name": "Angers", "id": 353196}, {"name": "Administration_publique_en_France", "id": 1286193}, {"name": "Organisation_internationale", "id": 96531}], "successors": [{"name": "Évêque_d'Angers", "id": 1125932}, {"name": "Joueur_du_SCO_Angers", "id": 1981252}, {"name": "Naissance_à_Angers", "id": 2097861}, {"name": "Maire_d'Angers", "id": 3826433}, {"name": "Joueur_de_l'Association_des_sports_de_glisse_d'Angers", "id": 5203700}, {"name": "Décès_à_Angers", "id": 6810412}]}