{"name": "Personnalité_féminine_japonaise", "id": 1286511, "predecessors": [{"name": "Genre_(sciences_sociales)", "id": 6120944}, {"name": "Accueil", "id": 1155637}, {"name": "Sciences_humaines_et_sociales", "id": 2320561}], "successors": [{"name": "Actrice_japonaise", "id": 87961}, {"name": "Femme_de_lettres_japonaise", "id": 4012647}, {"name": "Femme_du_Japon_médiéval", "id": 7089822}, {"name": "Femme_politique_japonaise", "id": 8012973}, {"name": "Mannequin_femme_japonais", "id": 9294696}, {"name": "Joueuse_japonaise_de_tennis", "id": 640494}, {"name": "Judokate_japonaise", "id": 1327106}, {"name": "Joueuse_japonaise_de_volley-ball", "id": 1927177}, {"name": "Joueuse_japonaise_de_softball", "id": 7366175}]}