{"name": "Langue_russe", "id": 129703, "predecessors": [{"name": "Langue_accentuelle", "id": 503335}, {"name": "Inventaire_de_familles_de_langues", "id": 13855860}], "successors": [{"name": "Presse_écrite_en_russe", "id": 1364460}, {"name": "Traducteur_vers_le_russe", "id": 2090384}, {"name": "Traducteur_depuis_le_russe", "id": 2190335}, {"name": "Film_en_russe", "id": 9476098}, {"name": "Chanson_en_russe", "id": 10016236}, {"name": "Traductrice_russe", "id": 11053804}, {"name": "Traducteur_russe_du_XXe_siècle", "id": 15377324}, {"name": "Adaptation_d'une_nouvelle_russe_au_cinéma", "id": 13534813}, {"name": "Réalisateur_russe", "id": 125582}, {"name": "Scénariste_russe_de_cinéma", "id": 238285}, {"name": "Film_se_déroulant_en_Russie", "id": 5944245}, {"name": "Producteur_russe_de_cinéma", "id": 9853410}, {"name": "Acteur_russe_de_cinéma", "id": 13698495}, {"name": "Actrice_russe_de_cinéma", "id": 13698506}, {"name": "Film_russe_en_noir_et_blanc", "id": 7314426}, {"name": "Film_muet_russe", "id": 7843177}, {"name": "Réalisateur_ukrainien", "id": 348185}, {"name": "Film_se_déroulant_en_Ukraine", "id": 6419284}, {"name": "Actrice_ukrainienne_de_cinéma", "id": 14486372}, {"name": "Réalisateur_soviétique", "id": 428921}, {"name": "Scénariste_soviétique_de_cinéma", "id": 1308338}, {"name": "Acteur_soviétique_de_cinéma", "id": 14071849}, {"name": "Film_dramatique_russe", "id": 7191631}, {"name": "Film_d'action_russe", "id": 7191719}, {"name": "Film_historique_russe", "id": 7197456}, {"name": "Comédie_russe", "id": 7315503}, {"name": "Film_d'aventure_russe", "id": 7624519}]}