{"name": "Militaire_français_des_guerres_napoléoniennes", "id": 15278198, "predecessors": [{"name": "Militaire_français_du_XIXe_siècle", "id": 1401897}, {"name": "Militaire_du_Premier_Empire", "id": 2709099}, {"name": "Personnalité_française_du_XIXe_siècle", "id": 779342}, {"name": "Forces_armées_de_la_France", "id": 206663}], "successors": [{"name": "Militaire_français_mort_au_combat_lors_des_guerres_napoléoniennes", "id": 15278208}, {"name": "Chef_militaire_français_des_guerres_napoléoniennes", "id": 15278965}]}