{"name": "Ancienne_sous-préfecture", "id": 263752, "predecessors": [{"name": "Ancien_arrondissement_en_France", "id": 826467}, {"name": "Sous-préfecture_française", "id": 4158001}], "successors": [{"name": "Cologne", "id": 307335}, {"name": "Naissance_à_Hasselt", "id": 3651918}, {"name": "Naissance_à_Lectoure", "id": 4142658}, {"name": "Personnalité_liée_à_Lectoure", "id": 11548697}, {"name": "Naissance_à_Amersfoort", "id": 4120727}, {"name": "Naissance_à_Nivelles", "id": 3873443}, {"name": "Naissance_à_Krefeld", "id": 6078546}, {"name": "Grand_Prix_Jef_Scherens", "id": 8303157}, {"name": "Joueur_de_l'AC_Arezzo", "id": 6135682}, {"name": "Joueur_du_Heracles_Almelo", "id": 3504754}, {"name": "Joueur_du_HFC_Haarlem", "id": 3506930}, {"name": "Naissance_à_Haarlem", "id": 3714711}, {"name": "Décès_à_Haarlem", "id": 6663859}, {"name": "Membre_de_la_guilde_de_Saint-Luc_de_Haarlem", "id": 9292647}, {"name": "Joueur_de_l'AZ_Alkmaar", "id": 3160355}, {"name": "Naissance_à_Alkmaar", "id": 4116211}]}