{"name": "Université_en_Italie", "id": 271005, "predecessors": [{"name": "Enseignement_supérieur", "id": 332674}, {"name": "Éducation", "id": 84941}], "successors": [{"name": "Universitaire_italien", "id": 1584160}, {"name": "Étudiant_de_l'université_pontificale_grégorienne", "id": 5933810}, {"name": "Professeur_à_l'université_pontificale_grégorienne", "id": 5935062}, {"name": "Étudiant_de_l'université_catholique_du_Sacré-Cœur", "id": 7297731}, {"name": "Professeur_à_l'université_de_Rome_«_La_Sapienza_»", "id": 5854794}, {"name": "Étudiant_de_l'université_de_Rome_«_La_Sapienza_»", "id": 7723932}, {"name": "Étudiant_de_l'université_pontificale_urbanienne", "id": 8177701}, {"name": "Professeur_à_l'université_de_Florence", "id": 5025846}, {"name": "Étudiant_de_l'université_de_Florence", "id": 5270877}, {"name": "Élève_de_l'École_normale_supérieure_de_Pise", "id": 5447255}, {"name": "Milan", "id": 113011}, {"name": "Professeur_à_l'université_de_Pavie", "id": 5026128}, {"name": "Étudiant_de_l'université_de_Pavie", "id": 5270884}, {"name": "Professeur_à_l'université_de_Milan", "id": 5025748}, {"name": "Étudiant_de_l'université_de_Milan", "id": 5270886}, {"name": "Étudiant_de_l'université_Bocconi_de_Milan", "id": 5865116}]}