{"name": "Commune_en_Bavière", "id": 2856275, "predecessors": [{"name": "Géographie_de_la_Bavière", "id": 1760384}, {"name": "Administration_territoriale", "id": 434707}], "successors": [{"name": "Ville_en_Bavière", "id": 477182}, {"name": "Wurtzbourg", "id": 1613301}, {"name": "Bourg_de_Bavière", "id": 9554555}, {"name": "Entreprise_ayant_son_siège_à_Munich", "id": 5600811}, {"name": "Procès_de_Nuremberg", "id": 2480297}, {"name": "Naissance_à_Nuremberg", "id": 4259063}, {"name": "Décès_à_Nuremberg", "id": 6815004}, {"name": "Naissance_à_Bamberg", "id": 4520189}, {"name": "Évêque_de_Bamberg", "id": 6222333}, {"name": "Décès_à_Bamberg", "id": 6810564}, {"name": "Naissance_à_Ratisbonne", "id": 4482538}, {"name": "Évêque_de_Ratisbonne", "id": 6220966}, {"name": "Décès_à_Ratisbonne", "id": 7870196}, {"name": "Naissance_à_Cobourg", "id": 5578912}, {"name": "Décès_à_Cobourg", "id": 7870141}, {"name": "Évêque_d'Eichstätt", "id": 6218805}, {"name": "Naissance_à_Garmisch-Partenkirchen", "id": 5579273}, {"name": "Décès_à_Garmisch-Partenkirchen", "id": 7170648}, {"name": "Personnalité_morte_au_camp_de_concentration_de_Dachau", "id": 15166847}, {"name": "Naissance_à_Bayreuth", "id": 4403261}, {"name": "Naissance_à_Erlangen", "id": 4456658}, {"name": "Décès_à_Erlangen", "id": 6945728}, {"name": "Naissance_à_Fürth", "id": 3040762}, {"name": "Naissance_à_Berchtesgaden", "id": 5578824}, {"name": "Joueur_du_EV_Landshut", "id": 4334806}, {"name": "Naissance_à_Landshut", "id": 9799149}, {"name": "Naissance_à_Ansbach", "id": 4519630}, {"name": "Naissance_à_Aschaffenbourg", "id": 5578581}, {"name": "Décès_à_Starnberg", "id": 12237338}, {"name": "Étudiant_de_l'université_Friedrich-Alexander_d'Erlangen-Nuremberg", "id": 6549753}, {"name": "Professeur_à_l'université_Friedrich-Alexander_d'Erlangen-Nuremberg", "id": 6550113}, {"name": "Naissance_à_Augsbourg", "id": 4003204}, {"name": "Évêque_d'Augsbourg", "id": 5589084}, {"name": "Décès_à_Augsbourg", "id": 7633915}]}