{"name": "Naissance_au_Nigeria", "id": 3127002, "predecessors": [{"name": "Géographie_économique", "id": 608974}, {"name": "Astronomie", "id": 80753}, {"name": "Accueil", "id": 1155637}], "successors": [{"name": "Naissance_au_Cameroun_britannique", "id": 9989963}, {"name": "Naissance_dans_la_colonie_et_protectorat_du_Nigeria", "id": 14038724}, {"name": "Naissance_à_Lagos", "id": 4039847}, {"name": "Naissance_à_Kaduna", "id": 7174621}, {"name": "Naissance_à_Ibadan", "id": 7364406}, {"name": "Naissance_à_Port_Harcourt", "id": 7364442}, {"name": "Naissance_à_Benin_City", "id": 7364446}]}