{"name": "Auckland", "id": 3846043, "predecessors": [{"name": "Ancienne_capitale_de_pays", "id": 467484}, {"name": "Jeux_du_Commonwealth", "id": 1356278}, {"name": "Île_de_l'océan_Pacifique_Sud", "id": 1908973}, {"name": "Accueil", "id": 1155637}, {"name": "Ville_en_Nouvelle-Zélande", "id": 185827}], "successors": [{"name": "Naissance_à_Auckland", "id": 3846150}, {"name": "Décès_à_Auckland", "id": 7009144}, {"name": "Banlieue_d'Auckland", "id": 13890003}, {"name": "Tournoi_de_tennis_d'Auckland", "id": 2714142}, {"name": "Étudiant_de_l'université_d'Auckland", "id": 7012293}]}