{"name": "Histoire_militaire_du_Japon", "id": 5012273, "predecessors": [{"name": "Histoire_militaire", "id": 82511}, {"name": "Histoire_de_l'Asie", "id": 616011}], "successors": [{"name": "Bataille_impliquant_le_Japon", "id": 796045}, {"name": "Histoire_de_l'aviation_japonaise", "id": 5832530}, {"name": "Histoire_militaire_du_Japon_durant_la_Seconde_Guerre_mondiale", "id": 7093615}, {"name": "Bataille_de_l'époque_Sengoku", "id": 7880260}, {"name": "Bataille_de_l'époque_Azuchi_Momoyama", "id": 7918371}, {"name": "Amiral_japonais", "id": 1080339}, {"name": "Général_japonais", "id": 3136662}, {"name": "Marine_impériale_japonaise", "id": 5264507}, {"name": "Nom_de_bateau_de_la_Marine_japonaise", "id": 11014197}, {"name": "Militaire_japonais_de_la_Seconde_Guerre_mondiale", "id": 1024486}, {"name": "Personnalité_militaire_japonaise_de_la_guerre_russo-japonaise", "id": 10468132}, {"name": "Samouraï_du_XXe_siècle", "id": 15267275}, {"name": "Amiral_japonais_du_XXe_siècle", "id": 15393286}, {"name": "Samouraï_du_XIXe_siècle", "id": 15267264}, {"name": "Militaire_japonais_de_la_première_guerre_sino-japonaise", "id": 15268252}, {"name": "Samouraï_du_XVIIe_siècle", "id": 15267247}, {"name": "Samouraï_du_XIIe_siècle", "id": 15267236}]}