{"name": "Histoire_de_la_Norvège", "id": 5266938, "predecessors": [{"name": "Histoire_de_l'Europe", "id": 192790}, {"name": "Concept_de_philosophie_politique", "id": 4745648}], "successors": [{"name": "Traité_signé_par_la_Norvège", "id": 3626975}, {"name": "Patronyme_norvégien", "id": 6260024}, {"name": "Maison_Bernadotte", "id": 777311}, {"name": "Ancienne_commune_en_Norvège", "id": 6634787}, {"name": "Naissance_à_Bergen_(Norvège)", "id": 4030164}, {"name": "Championnat_de_Norvège_de_football", "id": 4358231}]}