{"name": "Parti_politique_écosocialiste", "id": 6413337, "predecessors": [{"name": "Organisation_anticapitaliste", "id": 9175300}, {"name": "Parti_politique_de_gauche_antilibéral", "id": 8693569}, {"name": "Idéologie_politique", "id": 9366010}, {"name": "Accueil", "id": 1155637}, {"name": "Responsabilité_sociétale_des_entreprises", "id": 1527459}], "successors": [{"name": "Personnalité_de_Podemos_(parti_espagnol)", "id": 8081617}, {"name": "Député_membre_de_La_France_insoumise", "id": 10986456}]}