{"name": "Nouvelle-France", "id": 745978, "predecessors": [{"name": "Ancien_Régime", "id": 102977}, {"name": "Colonisation_des_Amériques", "id": 1464156}, {"name": "Politique", "id": 84966}, {"name": "Histoire_moderne", "id": 84892}], "successors": [{"name": "Histoire_coloniale_des_États-Unis", "id": 499505}, {"name": "Personnalité_de_la_Nouvelle-France", "id": 688721}, {"name": "Histoire_de_l'Acadie", "id": 964647}, {"name": "Éphéméride_de_la_Nouvelle-France", "id": 1198387}, {"name": "Ojibwé", "id": 3327137}, {"name": "Fort_français_en_Nouvelle-France", "id": 4070949}, {"name": "Chronologie_du_Canada_au_XVIIIe_siècle", "id": 4258370}, {"name": "Naissance_en_Nouvelle-France", "id": 4313276}, {"name": "Village_de_Nouvelle-France", "id": 4948277}, {"name": "Personnalité_liée_à_la_Louisiane", "id": 5016836}, {"name": "Cris", "id": 6390014}, {"name": "Décès_en_Nouvelle-France", "id": 6777920}, {"name": "Toponyme_micmac", "id": 4539819}, {"name": "Jésuite_canadien", "id": 1149291}, {"name": "Personnalité_religieuse_de_la_Nouvelle-France", "id": 14671867}]}