{"name": "Entreprise_ayant_son_siège_en_Chine", "id": 7958042, "predecessors": [{"name": "Économie_en_Chine", "id": 6818694}, {"name": "Accueil", "id": 1155637}], "successors": [{"name": "Entreprise_publique_en_Chine", "id": 3936997}, {"name": "Entreprise_ayant_son_siège_dans_la_région_administrative_spéciale_de_Hong_Kong", "id": 7909005}, {"name": "Entreprise_du_SSE_50", "id": 1938358}, {"name": "Entreprise_ayant_son_siège_à_Pékin", "id": 3417185}, {"name": "Entreprise_ayant_son_siège_à_Shanghai", "id": 3417236}, {"name": "Constructeur_automobile_ayant_son_siège_en_Chine", "id": 1594471}]}